yoku/bot.py
yoku/botutils.py
yoku/consts.py
yoku/database.py
yoku/scrape.py
Yoku-1.0.8.dist-info/METADATA
Yoku-1.0.8.dist-info/WHEEL
Yoku-1.0.8.dist-info/entry_points.txt
Yoku-1.0.8.dist-info/top_level.txt
Yoku-1.0.8.dist-info/RECORD
