Metadata-Version: 2.1
Name: Yoku
Version: 1.0.8
Summary: A minimal Yahoo! Auctions scraper.
Home-page: UNKNOWN
License: UNKNOWN
Platform: UNKNOWN
Requires-Dist: requests (>=2.26.0)
Requires-Dist: python-telegram-bot (<20.0.0,>=13.15)
Requires-Dist: beautifulsoup4 (>=4.11.1)
Requires-Dist: tinydb (>=4.7.0)
Requires-Dist: lxml (>=4.9.1)
